{"race": {"year": 2025, "eventName": "United States Grand Prix", "roundNumber": 19, "isFuture": false, "usedQualiGrid": true}, "predictionsFiltered": [{"rank": 1, "driverName": "VER", "driverNumber": 1, "predictedPosition": 1.4365627765655518, "actualPosition": 1, "gridPosition": 1, "constructor": null, "filterReason": null, "isFiltered": false}, {"rank": 2, "driverName": "NOR", "driverNumber": 4, "predictedPosition": 2.0414788722991943, "actualPosition": 2, "gridPosition": 2, "constructor": null, "filterReason": null, "isFiltered": false}, {"rank": 3, "driverName": "PIA", "driverNumber": 81, "predictedPosition": 2.9202518463134766, "actualPosition": 5, "gridPosition": 6, "constructor": null, "filterReason": null, "isFiltered": false}, {"rank": 4, "driverName": "RUS", "driverNumber": 63, "predictedPosition": 3.0578560829162598, "actualPosition": 6, "gridPosition": 4, "constructor": null, "filterReason": null, "isFiltered": false}, {"rank": 5, "driverName": "LEC", "driverNumber": 16, "predictedPosition": 3.499852418899536, "actualPosition": 3, "gridPosition": 3, "constructor": null, "filterReason": null, "isFiltered": false}, {"rank": 6, "driverName": "HAM", "driverNumber": 44, "predictedPosition": 4.247772216796875, "actualPosition": 4, "gridPosition": 5, "constructor": null, "filterReason": null, "isFiltered": false}, {"rank": 7, "driverName": "ANT", "driverNumber": 12, "predictedPosition": 5.501468658447266, "actualPosition": 13, "gridPosition": 7, "constructor": null, "filterReason": null, "isFiltered": false}, {"rank": 9, "driverName": "BEA", "driverNumber": 87, "predictedPosition": 7.527655124664307, "actualPosition": 9, "gridPosition": 8, "constructor": null, "filterReason": null, "isFiltered": false}, {"rank": 10, "driverName": "LAW", "driverNumber": 30, "predictedPosition": 7.547667503356934, "actualPosition": 11, "gridPosition": 12, "constructor": null, "filterReason": null, "isFiltered": false}], "predictionsUnfiltered": [{"rank": 1, "driverName": "VER", "driverNumber": 1, "predictedPosition": 1.4365627765655518, "actualPosition": 1, "gridPosition": 1, "constructor": null, "filterReason": null, "isFiltered": false}, {"rank": 2, "driverName": "NOR", "driverNumber": 4, "predictedPosition": 2.0414788722991943, "actualPosition": 2, "gridPosition": 2, "constructor": null, "filterReason": null, "isFiltered": false}, {"rank": 3, "driverName": "PIA", "driverNumber": 81, "predictedPosition": 2.9202518463134766, "actualPosition": 5, "gridPosition": 6, "constructor": null, "filterReason": null, "isFiltered": false}, {"rank": 4, "driverName": "RUS", "driverNumber": 63, "predictedPosition": 3.0578560829162598, "actualPosition": 6, "gridPosition": 4, "constructor": null, "filterReason": null, "isFiltered": false}, {"rank": 5, "driverName": "LEC", "driverNumber": 16, "predictedPosition": 3.499852418899536, "actualPosition": 3, "gridPosition": 3, "constructor": null, "filterReason": null, "isFiltered": false}, {"rank": 6, "driverName": "HAM", "driverNumber": 44, "predictedPosition": 4.247772216796875, "actualPosition": 4, "gridPosition": 5, "constructor": null, "filterReason": null, "isFiltered": false}, {"rank": 7, "driverName": "ANT", "driverNumber": 12, "predictedPosition": 5.501468658447266, "actualPosition": 13, "gridPosition": 7, "constructor": null, "filterReason": null, "isFiltered": false}, {"rank": 8, "driverName": "SAI", "driverNumber": 55, "predictedPosition": 7.282266139984131, "actualPosition": 20, "gridPosition": 9, "constructor": null, "filterReason": "Dropped 11 places (grid 9 \u2192 finish 20)", "isFiltered": true}, {"rank": 9, "driverName": "BEA", "driverNumber": 87, "predictedPosition": 7.527655124664307, "actualPosition": 9, "gridPosition": 8, "constructor": null, "filterReason": null, "isFiltered": false}, {"rank": 10, "driverName": "LAW", "driverNumber": 30, "predictedPosition": 7.547667503356934, "actualPosition": 11, "gridPosition": 12, "constructor": null, "filterReason": null, "isFiltered": false}], "totalDrivers": 20}