{"race": {"year": 2025, "eventName": "Monaco Grand Prix", "roundNumber": 8, "isFuture": false, "usedQualiGrid": true}, "predictionsFiltered": [{"rank": 1, "driverName": "NOR", "driverNumber": 4, "predictedPosition": 1.282110184431076, "actualPosition": 1, "gridPosition": 1, "constructor": null, "filterReason": null, "isFiltered": false}, {"rank": 2, "driverName": "LEC", "driverNumber": 16, "predictedPosition": 2.3999947905540466, "actualPosition": 2, "gridPosition": 2, "constructor": null, "filterReason": null, "isFiltered": false}, {"rank": 3, "driverName": "PIA", "driverNumber": 81, "predictedPosition": 2.925016336143017, "actualPosition": 3, "gridPosition": 3, "constructor": null, "filterReason": null, "isFiltered": false}, {"rank": 4, "driverName": "VER", "driverNumber": 1, "predictedPosition": 3.705047369003296, "actualPosition": 4, "gridPosition": 4, "constructor": null, "filterReason": null, "isFiltered": false}, {"rank": 5, "driverName": "HAM", "driverNumber": 44, "predictedPosition": 6.0839996337890625, "actualPosition": 5, "gridPosition": 7, "constructor": null, "filterReason": null, "isFiltered": false}, {"rank": 7, "driverName": "HAD", "driverNumber": 6, "predictedPosition": 6.722663760185242, "actualPosition": 6, "gridPosition": 5, "constructor": null, "filterReason": null, "isFiltered": false}, {"rank": 8, "driverName": "OCO", "driverNumber": 31, "predictedPosition": 8.706357955932617, "actualPosition": 7, "gridPosition": 8, "constructor": null, "filterReason": null, "isFiltered": false}, {"rank": 9, "driverName": "LAW", "driverNumber": 30, "predictedPosition": 8.868639975786209, "actualPosition": 8, "gridPosition": 9, "constructor": null, "filterReason": null, "isFiltered": false}, {"rank": 10, "driverName": "ALB", "driverNumber": 23, "predictedPosition": 9.587277352809906, "actualPosition": 9, "gridPosition": 10, "constructor": null, "filterReason": null, "isFiltered": false}], "predictionsUnfiltered": [{"rank": 1, "driverName": "NOR", "driverNumber": 4, "predictedPosition": 1.282110184431076, "actualPosition": 1, "gridPosition": 1, "constructor": null, "filterReason": null, "isFiltered": false}, {"rank": 2, "driverName": "LEC", "driverNumber": 16, "predictedPosition": 2.3999947905540466, "actualPosition": 2, "gridPosition": 2, "constructor": null, "filterReason": null, "isFiltered": false}, {"rank": 3, "driverName": "PIA", "driverNumber": 81, "predictedPosition": 2.925016336143017, "actualPosition": 3, "gridPosition": 3, "constructor": null, "filterReason": null, "isFiltered": false}, {"rank": 4, "driverName": "VER", "driverNumber": 1, "predictedPosition": 3.705047369003296, "actualPosition": 4, "gridPosition": 4, "constructor": null, "filterReason": null, "isFiltered": false}, {"rank": 5, "driverName": "HAM", "driverNumber": 44, "predictedPosition": 6.0839996337890625, "actualPosition": 5, "gridPosition": 7, "constructor": null, "filterReason": null, "isFiltered": false}, {"rank": 6, "driverName": "ALO", "driverNumber": 14, "predictedPosition": 6.6972092390060425, "actualPosition": 19, "gridPosition": 6, "constructor": null, "filterReason": "Dropped 13 places (grid 6 \u2192 finish 19)", "isFiltered": true}, {"rank": 7, "driverName": "HAD", "driverNumber": 6, "predictedPosition": 6.722663760185242, "actualPosition": 6, "gridPosition": 5, "constructor": null, "filterReason": null, "isFiltered": false}, {"rank": 8, "driverName": "OCO", "driverNumber": 31, "predictedPosition": 8.706357955932617, "actualPosition": 7, "gridPosition": 8, "constructor": null, "filterReason": null, "isFiltered": false}, {"rank": 9, "driverName": "LAW", "driverNumber": 30, "predictedPosition": 8.868639975786209, "actualPosition": 8, "gridPosition": 9, "constructor": null, "filterReason": null, "isFiltered": false}, {"rank": 10, "driverName": "ALB", "driverNumber": 23, "predictedPosition": 9.587277352809906, "actualPosition": 9, "gridPosition": 10, "constructor": null, "filterReason": null, "isFiltered": false}], "totalDrivers": 20}